telegrambot/__init__.py
telegrambot/__main__.py
telegrambot/bot.py
telegrambot/cli.py
telegrambot/utils.py
ciresbot-0.2.4.dist-info/LICENSE
ciresbot-0.2.4.dist-info/METADATA
ciresbot-0.2.4.dist-info/WHEEL
ciresbot-0.2.4.dist-info/entry_points.txt
ciresbot-0.2.4.dist-info/top_level.txt
ciresbot-0.2.4.dist-info/RECORD
