Metadata-Version: 2.1
Name: ciresbot
Version: 0.2.4
Summary: Telegram bot
Author-email: Daniel Ibarrola <daniel.ibarrola.sanchez@gmail.com>
Project-URL: Homepage, https://github.com/Daniel-Ibarrola/TelegramBot.git
Keywords: telegram,bot,messaging
Classifier: Programming Language :: Python
Classifier: Programming Language :: Python :: 3
Requires-Python: >=3.11
License-File: LICENSE
Provides-Extra: dev
Requires-Dist: bumpver ; extra == 'dev'
Requires-Dist: pytest ; extra == 'dev'
